MANIFEST.in
requirements-test.txt
requirements.txt
setup.py
planner/__init__.py
planner/abstfilter.py
planner/constants.py
planner/ordereddict.py
planner/planner.py
planner/sexpr.py
planner.egg-info/PKG-INFO
planner.egg-info/SOURCES.txt
planner.egg-info/dependency_links.txt
planner.egg-info/not-zip-safe
planner.egg-info/requires.txt
planner.egg-info/top_level.txt
planner/tests/__init__.py
planner/tests/test_blocks.py
planner/tests/test_driving.py
planner/tests/test_general.py
planner/tests/test_mindswap.py
planner/tests/xo.py
planner/tests/domains/__init__.py
planner/tests/domains/blocks/__init__.py
planner/tests/domains/blocks/__init__.pyc
planner/tests/domains/blocks/domain.yml
planner/tests/domains/blocks/problem1.txt
planner/tests/domains/driving/__init__.py
planner/tests/domains/driving/__init__.pyc
planner/tests/domains/driving/connections.csv
planner/tests/domains/driving/domain.yml
planner/tests/domains/driving/map.py
planner/tests/domains/driving/map.pyc
planner/tests/domains/driving/points.csv
planner/tests/domains/driving/problem.txt
planner/tests/domains/mindswap/__init__.py
planner/tests/domains/mindswap/__init__.pyc
planner/tests/domains/mindswap/domain-new.txt
planner/tests/domains/mindswap/domain-oav.txt
planner/tests/domains/mindswap/domain-old.txt
planner/tests/domains/mindswap/domain.yml
planner/tests/domains/mindswap/domain2.yml
planner/tests/domains/mindswap/problem-new.txt
planner/tests/domains/mindswap/problem-new.yml
planner/tests/domains/mindswap/problem-old.txt
planner/tests/domains/mindswap/problem.yml
planner/tests/domains/xo/__init__.py
planner/tests/domains/xo/__init__.pyc
planner/tests/domains/xo/domain.yml